{
  "updated": 1773509762793,
  "ranks": [
    {
      "address": "0xcde991ff0f20e4ab3896d2f11ab33ad4e0bdcf03",
      "chains": [
        "bsc"
      ],
      "totalTokens": 2,
      "trackedTokens": 2,
      "wins": 1,
      "losses": 1,
      "winRate": 50,
      "avgReturn": 332.8,
      "score": 263.72,
      "firstSeen": 1773506911854,
      "topPicks": [
        {
          "symbol": "人生",
          "chain": "bsc",
          "change": 670.0183715798306
        },
        {
          "symbol": "MOONDOGE",
          "chain": "bsc",
          "change": -4.47212373066357
        }
      ]
    },
    {
      "address": "0x0c64719cdaed5500e0ec82ab8c3280674ced8a05",
      "chains": [
        "bsc"
      ],
      "totalTokens": 2,
      "trackedTokens": 2,
      "wins": 1,
      "losses": 1,
      "winRate": 50,
      "avgReturn": 288.1,
      "score": 228.35,
      "firstSeen": 1773506911854,
      "topPicks": [
        {
          "symbol": "人生",
          "chain": "bsc",
          "change": 670.0183715798306
        },
        {
          "symbol": "FAFO",
          "chain": "bsc",
          "change": -93.7211149521641
        }
      ]
    },
    {
      "address": "9ovjQQ9SRFNPiFn1be3JVLTabc3kjEvnoDrKThHSsjRv",
      "chains": [
        "solana"
      ],
      "totalTokens": 5,
      "trackedTokens": 5,
      "wins": 2,
      "losses": 3,
      "winRate": 40,
      "avgReturn": 191.9,
      "score": 198.38,
      "firstSeen": 1773506911627,
      "topPicks": [
        {
          "symbol": "Rosie",
          "chain": "solana",
          "change": 1072.4675863498535
        },
        {
          "symbol": "TERAFAB",
          "chain": "solana",
          "change": 101.97536752769005
        },
        {
          "symbol": "NORWOOD",
          "chain": "solana",
          "change": -45.34398205697774
        },
        {
          "symbol": "AI",
          "chain": "solana",
          "change": -78.20672337114156
        },
        {
          "symbol": "ZEZE",
          "chain": "solana",
          "change": -91.57332302783125
        }
      ]
    },
    {
      "address": "C3d6GcXo1QrwNHAVJWjPjTGHbq7b6xM4ezEgZthMnype",
      "chains": [
        "solana"
      ],
      "totalTokens": 7,
      "trackedTokens": 4,
      "wins": 1,
      "losses": 3,
      "winRate": 25,
      "avgReturn": 240.9,
      "score": 139.86,
      "firstSeen": 1773506911627,
      "topPicks": [
        {
          "symbol": "Rosie",
          "chain": "solana",
          "change": 1072.4675863498535
        },
        {
          "symbol": "WENDYS",
          "chain": "solana",
          "change": -1.4842468137427312
        },
        {
          "symbol": "SMITH",
          "chain": "solana",
          "change": -18.59305456737125
        },
        {
          "symbol": "X COINS",
          "chain": "solana",
          "change": -88.65825919408314
        }
      ]
    },
    {
      "address": "7Lc3AxNXjeDrcD7Uv2p9aXwHgrU5BreefXgfwQQiNfXY",
      "chains": [
        "solana"
      ],
      "totalTokens": 6,
      "trackedTokens": 6,
      "wins": 2,
      "losses": 4,
      "winRate": 33.3,
      "avgReturn": 144.4,
      "score": 135.14,
      "firstSeen": 1773506911627,
      "topPicks": [
        {
          "symbol": "Rosie",
          "chain": "solana",
          "change": 1072.4675863498535
        },
        {
          "symbol": "TERAFAB",
          "chain": "solana",
          "change": 101.97536752769005
        },
        {
          "symbol": "NORWOOD",
          "chain": "solana",
          "change": -45.34398205697774
        },
        {
          "symbol": "AI",
          "chain": "solana",
          "change": -78.20672337114156
        },
        {
          "symbol": "ZEZE",
          "chain": "solana",
          "change": -91.57332302783125
        }
      ]
    },
    {
      "address": "0x9172522708770b2eac035c7a9a313aa4362d6bad",
      "chains": [
        "bsc"
      ],
      "totalTokens": 4,
      "trackedTokens": 3,
      "wins": 1,
      "losses": 2,
      "winRate": 33.3,
      "avgReturn": 164.9,
      "score": 109.96,
      "firstSeen": 1773506911853,
      "topPicks": [
        {
          "symbol": "人生",
          "chain": "bsc",
          "change": 670.0183715798306
        },
        {
          "symbol": "波龙",
          "chain": "bsc",
          "change": -77.83415715079039
        },
        {
          "symbol": "波龙",
          "chain": "bsc",
          "change": -97.37666089303639
        }
      ]
    },
    {
      "address": "0x9fcdadd620518e2af33176fe4a086bbafa7837e1",
      "chains": [
        "bsc"
      ],
      "totalTokens": 3,
      "trackedTokens": 3,
      "wins": 1,
      "losses": 2,
      "winRate": 33.3,
      "avgReturn": 163.9,
      "score": 109.26,
      "firstSeen": 1773506911854,
      "topPicks": [
        {
          "symbol": "人生",
          "chain": "bsc",
          "change": 670.0183715798306
        },
        {
          "symbol": "MOONDOGECOIN",
          "chain": "bsc",
          "change": -84.60505860322087
        },
        {
          "symbol": "FAFO",
          "chain": "bsc",
          "change": -93.7211149521641
        }
      ]
    },
    {
      "address": "0x46072e45b1425766a6878c2730d3ce9c084d3733",
      "chains": [
        "bsc"
      ],
      "totalTokens": 2,
      "trackedTokens": 2,
      "wins": 2,
      "losses": 0,
      "winRate": 100,
      "avgReturn": 59.5,
      "score": 94.36,
      "firstSeen": 1773506911854,
      "topPicks": [
        {
          "symbol": "TOM",
          "chain": "bsc",
          "change": 92.67627153258417
        },
        {
          "symbol": "AI果蝇",
          "chain": "bsc",
          "change": 26.397463790818747
        }
      ]
    },
    {
      "address": "0xecea32d3933b579e64843e66ff41209d6052a956",
      "chains": [
        "bsc"
      ],
      "totalTokens": 3,
      "trackedTokens": 2,
      "wins": 1,
      "losses": 1,
      "winRate": 50,
      "avgReturn": 44.1,
      "score": 34.95,
      "firstSeen": 1773506911853,
      "topPicks": [
        {
          "symbol": "TOM",
          "chain": "bsc",
          "change": 92.67627153258417
        },
        {
          "symbol": "MOONDOGE",
          "chain": "bsc",
          "change": -4.47212373066357
        }
      ]
    },
    {
      "address": "0x62a4de6956328885c90a8d3f4b364f901aebfc15",
      "chains": [
        "base"
      ],
      "totalTokens": 3,
      "trackedTokens": 2,
      "wins": 2,
      "losses": 0,
      "winRate": 100,
      "avgReturn": 21.5,
      "score": 34.08,
      "firstSeen": 1773508066758,
      "topPicks": [
        {
          "symbol": "NOOK",
          "chain": "base",
          "change": 23.98234998739617
        },
        {
          "symbol": "Molten",
          "chain": "base",
          "change": 19.018414101426544
        }
      ]
    },
    {
      "address": "0x0b7cd8b4e9b4648595d338252b507c95f46a9dae",
      "chains": [
        "base"
      ],
      "totalTokens": 2,
      "trackedTokens": 2,
      "wins": 2,
      "losses": 0,
      "winRate": 100,
      "avgReturn": 20.2,
      "score": 32,
      "firstSeen": 1773508066759,
      "topPicks": [
        {
          "symbol": "JUNO",
          "chain": "base",
          "change": 40.234492206838354
        },
        {
          "symbol": "NOX",
          "chain": "base",
          "change": 0.14369912130168133
        }
      ]
    },
    {
      "address": "0xbc1b1c1627b4cc0bb2bb5e28de8fdf241bbb3e18",
      "chains": [
        "bsc"
      ],
      "totalTokens": 3,
      "trackedTokens": 2,
      "wins": 2,
      "losses": 0,
      "winRate": 100,
      "avgReturn": 18.9,
      "score": 29.88,
      "firstSeen": 1773506911854,
      "topPicks": [
        {
          "symbol": "AI果蝇",
          "chain": "bsc",
          "change": 26.397463790818747
        },
        {
          "symbol": "WUKONG",
          "chain": "bsc",
          "change": 11.30493991265331
        }
      ]
    },
    {
      "address": "0x872340e9c05534e92104d81f5bd5a890765b6a99",
      "chains": [
        "base"
      ],
      "totalTokens": 2,
      "trackedTokens": 2,
      "wins": 2,
      "losses": 0,
      "winRate": 100,
      "avgReturn": 12.1,
      "score": 19.12,
      "firstSeen": 1773508066758,
      "topPicks": [
        {
          "symbol": "NOOK",
          "chain": "base",
          "change": 23.98234998739617
        },
        {
          "symbol": "NOX",
          "chain": "base",
          "change": 0.14369912130168133
        }
      ]
    },
    {
      "address": "0x9ffea936c96b7032f22255564d484d0888888888",
      "chains": [
        "bsc"
      ],
      "totalTokens": 3,
      "trackedTokens": 3,
      "wins": 2,
      "losses": 1,
      "winRate": 66.7,
      "avgReturn": 12.8,
      "score": 17,
      "firstSeen": 1773506911854,
      "topPicks": [
        {
          "symbol": "小龙虾",
          "chain": "bsc",
          "change": 52.890603262128266
        },
        {
          "symbol": "WUKONG",
          "chain": "bsc",
          "change": 11.30493991265331
        },
        {
          "symbol": "天梯",
          "chain": "bsc",
          "change": -25.93572786343937
        }
      ]
    },
    {
      "address": "0x38d020947cde613e2fa85bf1c6f703c74ada5d0b",
      "chains": [
        "base"
      ],
      "totalTokens": 2,
      "trackedTokens": 2,
      "wins": 1,
      "losses": 1,
      "winRate": 50,
      "avgReturn": 20,
      "score": 15.88,
      "firstSeen": 1773508066758,
      "topPicks": [
        {
          "symbol": "JUNO",
          "chain": "base",
          "change": 40.234492206838354
        },
        {
          "symbol": "MOLT",
          "chain": "base",
          "change": -0.1456610823546663
        }
      ]
    },
    {
      "address": "0xf154977eb88584660cb43467516126716938434a",
      "chains": [
        "bsc",
        "base"
      ],
      "totalTokens": 7,
      "trackedTokens": 7,
      "wins": 4,
      "losses": 3,
      "winRate": 57.1,
      "avgReturn": 8.6,
      "score": 14.82,
      "firstSeen": 1773506911854,
      "topPicks": [
        {
          "symbol": "JUNO",
          "chain": "base",
          "change": 40.234492206838354
        },
        {
          "symbol": "Molten",
          "chain": "base",
          "change": 19.018414101426544
        },
        {
          "symbol": "哭哭马",
          "chain": "bsc",
          "change": 3.9936861629979363
        },
        {
          "symbol": "Freedom of Money",
          "chain": "bsc",
          "change": 2.8392482726003965
        },
        {
          "symbol": "龙虾",
          "chain": "bsc",
          "change": -0.9611042648104693
        }
      ]
    },
    {
      "address": "0xf3cc3accbc3df0384d689585bbafdad268003b12",
      "chains": [
        "base"
      ],
      "totalTokens": 5,
      "trackedTokens": 3,
      "wins": 2,
      "losses": 1,
      "winRate": 66.7,
      "avgReturn": 10.9,
      "score": 14.52,
      "firstSeen": 1773508066758,
      "topPicks": [
        {
          "symbol": "Molten",
          "chain": "base",
          "change": 19.018414101426544
        },
        {
          "symbol": "FELIX",
          "chain": "base",
          "change": 13.808222315713525
        },
        {
          "symbol": "MOLT",
          "chain": "base",
          "change": -0.1456610823546663
        }
      ]
    },
    {
      "address": "0xb31bcbc718168fcf8b1aa99ac90c4ad98137e8f7",
      "chains": [
        "base"
      ],
      "totalTokens": 5,
      "trackedTokens": 4,
      "wins": 2,
      "losses": 2,
      "winRate": 50,
      "avgReturn": 12.3,
      "score": 14.25,
      "firstSeen": 1773508066758,
      "topPicks": [
        {
          "symbol": "STAKR",
          "chain": "base",
          "change": 63.97824260792292
        },
        {
          "symbol": "Doppel",
          "chain": "base",
          "change": 13.49120781765134
        },
        {
          "symbol": "cyb3rwr3n",
          "chain": "base",
          "change": -13.512263286004162
        },
        {
          "symbol": "DONUT",
          "chain": "base",
          "change": -14.865207448385451
        }
      ]
    },
    {
      "address": "9v3xeLZiWPevBN8ydoDdc7W6KRofScFKYsnizD9WZCmp",
      "chains": [
        "solana"
      ],
      "totalTokens": 8,
      "trackedTokens": 4,
      "wins": 1,
      "losses": 3,
      "winRate": 25,
      "avgReturn": 22.6,
      "score": 13.14,
      "firstSeen": 1773506911627,
      "topPicks": [
        {
          "symbol": "WARDOGS",
          "chain": "solana",
          "change": 113.20537189346797
        },
        {
          "symbol": "WENDYS",
          "chain": "solana",
          "change": -1.4842468137427312
        },
        {
          "symbol": "Memehouse",
          "chain": "solana",
          "change": -2.59255500031965
        },
        {
          "symbol": "SMITH",
          "chain": "solana",
          "change": -18.59305456737125
        }
      ]
    },
    {
      "address": "0x6e89ec9db4342eb5df24f864eedda3eac14d8666",
      "chains": [
        "bsc"
      ],
      "totalTokens": 3,
      "trackedTokens": 3,
      "wins": 2,
      "losses": 1,
      "winRate": 66.7,
      "avgReturn": 7.1,
      "score": 9.52,
      "firstSeen": 1773506911853,
      "topPicks": [
        {
          "symbol": "我是未来",
          "chain": "bsc",
          "change": 18.555598072032996
        },
        {
          "symbol": "MILADY",
          "chain": "bsc",
          "change": 4.956134992651621
        },
        {
          "symbol": "我的刀盾",
          "chain": "bsc",
          "change": -2.0978893799212193
        }
      ]
    },
    {
      "address": "0x537948624d4e8c4fa9cfcf8170906620d43b482c",
      "chains": [
        "base"
      ],
      "totalTokens": 2,
      "trackedTokens": 2,
      "wins": 1,
      "losses": 1,
      "winRate": 50,
      "avgReturn": 11.9,
      "score": 9.45,
      "firstSeen": 1773508066758,
      "topPicks": [
        {
          "symbol": "NOOK",
          "chain": "base",
          "change": 23.98234998739617
        },
        {
          "symbol": "MOLT",
          "chain": "base",
          "change": -0.1456610823546663
        }
      ]
    },
    {
      "address": "ALscTJDyAoBtRyJFr6J9h93DMY4DPh86cMwz6AaXdMaT",
      "chains": [
        "solana"
      ],
      "totalTokens": 3,
      "trackedTokens": 2,
      "wins": 1,
      "losses": 1,
      "winRate": 50,
      "avgReturn": 10.4,
      "score": 8.22,
      "firstSeen": 1773506911627,
      "topPicks": [
        {
          "symbol": "MERLIN",
          "chain": "solana",
          "change": 23.335016696188596
        },
        {
          "symbol": "Memehouse",
          "chain": "solana",
          "change": -2.59255500031965
        }
      ]
    },
    {
      "address": "0x3c8f6d1559d1e2e4f48d51b4bc5fdb5c783a8940",
      "chains": [
        "base"
      ],
      "totalTokens": 3,
      "trackedTokens": 2,
      "wins": 2,
      "losses": 0,
      "winRate": 100,
      "avgReturn": 5,
      "score": 7.96,
      "firstSeen": 1773508066758,
      "topPicks": [
        {
          "symbol": "ODAI",
          "chain": "base",
          "change": 9.895273999709998
        },
        {
          "symbol": "NOX",
          "chain": "base",
          "change": 0.14369912130168133
        }
      ]
    },
    {
      "address": "0xcc90cf56e5bd645974326111a86fd05da8ec2a2c",
      "chains": [
        "bsc"
      ],
      "totalTokens": 8,
      "trackedTokens": 7,
      "wins": 4,
      "losses": 3,
      "winRate": 57.1,
      "avgReturn": 3.6,
      "score": 6.12,
      "firstSeen": 1773506911853,
      "topPicks": [
        {
          "symbol": "我是未来",
          "chain": "bsc",
          "change": 18.555598072032996
        },
        {
          "symbol": "AGENT",
          "chain": "bsc",
          "change": 5.168375114683451
        },
        {
          "symbol": "哭哭马",
          "chain": "bsc",
          "change": 3.9936861629979363
        },
        {
          "symbol": "Freedom of Money",
          "chain": "bsc",
          "change": 2.8392482726003965
        },
        {
          "symbol": "龙虾",
          "chain": "bsc",
          "change": -0.9611042648104693
        }
      ]
    },
    {
      "address": "0xae425b91728436762762489df07b7d74963c85d0",
      "chains": [
        "bsc"
      ],
      "totalTokens": 7,
      "trackedTokens": 7,
      "wins": 4,
      "losses": 3,
      "winRate": 57.1,
      "avgReturn": 3.6,
      "score": 6.12,
      "firstSeen": 1773506911854,
      "topPicks": [
        {
          "symbol": "我是未来",
          "chain": "bsc",
          "change": 18.555598072032996
        },
        {
          "symbol": "AGENT",
          "chain": "bsc",
          "change": 5.168375114683451
        },
        {
          "symbol": "哭哭马",
          "chain": "bsc",
          "change": 3.9936861629979363
        },
        {
          "symbol": "Freedom of Money",
          "chain": "bsc",
          "change": 2.8392482726003965
        },
        {
          "symbol": "龙虾",
          "chain": "bsc",
          "change": -0.9611042648104693
        }
      ]
    },
    {
      "address": "0x8603a26ee4528f3ca11be876510a220d79819f31",
      "chains": [
        "base"
      ],
      "totalTokens": 6,
      "trackedTokens": 2,
      "wins": 1,
      "losses": 1,
      "winRate": 50,
      "avgReturn": 6.8,
      "score": 5.41,
      "firstSeen": 1773508066758,
      "topPicks": [
        {
          "symbol": "FELIX",
          "chain": "base",
          "change": 13.808222315713525
        },
        {
          "symbol": "MOLT",
          "chain": "base",
          "change": -0.1456610823546663
        }
      ]
    },
    {
      "address": "0xa42956220c136f6d8c5efb43480b1b8d28e317d7",
      "chains": [
        "base"
      ],
      "totalTokens": 2,
      "trackedTokens": 2,
      "wins": 1,
      "losses": 1,
      "winRate": 50,
      "avgReturn": 4.8,
      "score": 3.79,
      "firstSeen": 1773508066758,
      "topPicks": [
        {
          "symbol": "STAKR",
          "chain": "base",
          "change": 63.97824260792292
        },
        {
          "symbol": "WAFFLES",
          "chain": "base",
          "change": -54.414475543069955
        }
      ]
    },
    {
      "address": "0xadc62381399266cdd79a83295f0de14fef4c14b6",
      "chains": [
        "bsc"
      ],
      "totalTokens": 4,
      "trackedTokens": 3,
      "wins": 2,
      "losses": 1,
      "winRate": 66.7,
      "avgReturn": 2.5,
      "score": 3.38,
      "firstSeen": 1773506911853,
      "topPicks": [
        {
          "symbol": "AGENT",
          "chain": "bsc",
          "change": 5.168375114683451
        },
        {
          "symbol": "MILADY",
          "chain": "bsc",
          "change": 4.956134992651621
        },
        {
          "symbol": "Fight",
          "chain": "bsc",
          "change": -2.519284602892678
        }
      ]
    },
    {
      "address": "0x680bf9efe3d3d40ca28e4f028dfe2d99f985f969",
      "chains": [
        "bsc"
      ],
      "totalTokens": 5,
      "trackedTokens": 4,
      "wins": 1,
      "losses": 3,
      "winRate": 25,
      "avgReturn": 2.7,
      "score": 1.54,
      "firstSeen": 1773506911854,
      "topPicks": [
        {
          "symbol": "我是未来",
          "chain": "bsc",
          "change": 18.555598072032996
        },
        {
          "symbol": "龙虾",
          "chain": "bsc",
          "change": -0.9611042648104693
        },
        {
          "symbol": "Fight",
          "chain": "bsc",
          "change": -2.519284602892678
        },
        {
          "symbol": "MOONDOGE",
          "chain": "bsc",
          "change": -4.47212373066357
        }
      ]
    },
    {
      "address": "HDsxJuZSBRhiMJj56VAqhXTZNdFfwrvj2S6HpFsp8USn",
      "chains": [
        "solana"
      ],
      "totalTokens": 9,
      "trackedTokens": 3,
      "wins": 0,
      "losses": 3,
      "winRate": 0,
      "avgReturn": -56.8,
      "score": 0,
      "firstSeen": 1773506911627,
      "topPicks": [
        {
          "symbol": "SMITH",
          "chain": "solana",
          "change": -18.59305456737125
        },
        {
          "symbol": "dbxbx",
          "chain": "solana",
          "change": -54.59864063856453
        },
        {
          "symbol": "WHALE",
          "chain": "solana",
          "change": -97.2863916139708
        }
      ]
    },
    {
      "address": "CbvcMCacUisoBowPiPaX3P1eV4bA5HCeU5jEC7AM2G42",
      "chains": [
        "solana"
      ],
      "totalTokens": 7,
      "trackedTokens": 3,
      "wins": 1,
      "losses": 2,
      "winRate": 33.3,
      "avgReturn": -0.9,
      "score": 0,
      "firstSeen": 1773506911627,
      "topPicks": [
        {
          "symbol": "WARDOGS",
          "chain": "solana",
          "change": 113.20537189346797
        },
        {
          "symbol": "SMITH",
          "chain": "solana",
          "change": -18.59305456737125
        },
        {
          "symbol": "WHALE",
          "chain": "solana",
          "change": -97.2863916139708
        }
      ]
    },
    {
      "address": "5uuJVvx1Gq7qSjWubuyJcLnWSjX3SoceAzjN4KpAQxi6",
      "chains": [
        "solana"
      ],
      "totalTokens": 2,
      "trackedTokens": 2,
      "wins": 0,
      "losses": 2,
      "winRate": 0,
      "avgReturn": -47,
      "score": 0,
      "firstSeen": 1773506911627,
      "topPicks": [
        {
          "symbol": "HORSES",
          "chain": "solana",
          "change": -6.905944064051963
        },
        {
          "symbol": "FLOFLO",
          "chain": "solana",
          "change": -87.06084516345729
        }
      ]
    },
    {
      "address": "FveM6MArtgQatkay9FKVd3k8GmuTbQ5zNNL5qYVC1F48",
      "chains": [
        "solana"
      ],
      "totalTokens": 17,
      "trackedTokens": 8,
      "wins": 3,
      "losses": 5,
      "winRate": 37.5,
      "avgReturn": -4.5,
      "score": 0,
      "firstSeen": 1773506911627,
      "topPicks": [
        {
          "symbol": "WARDOGS",
          "chain": "solana",
          "change": 113.20537189346797
        },
        {
          "symbol": "TripleT",
          "chain": "solana",
          "change": 13.404924492299838
        },
        {
          "symbol": "Life",
          "chain": "solana",
          "change": 0.3626411156351229
        },
        {
          "symbol": "Distorted",
          "chain": "solana",
          "change": -2.491843543999448
        },
        {
          "symbol": "SMITH",
          "chain": "solana",
          "change": -18.59305456737125
        }
      ]
    },
    {
      "address": "G3zuTGfTRMLZK5YiQt5SHChwNpVsruEFACq4r2psmLzS",
      "chains": [
        "solana"
      ],
      "totalTokens": 8,
      "trackedTokens": 3,
      "wins": 0,
      "losses": 3,
      "winRate": 0,
      "avgReturn": -36.5,
      "score": 0,
      "firstSeen": 1773506911627,
      "topPicks": [
        {
          "symbol": "SMITH",
          "chain": "solana",
          "change": -18.59305456737125
        },
        {
          "symbol": "NORWOOD",
          "chain": "solana",
          "change": -45.34398205697774
        },
        {
          "symbol": "01001000",
          "chain": "solana",
          "change": -45.684243328451245
        }
      ]
    },
    {
      "address": "2Ft3YvLGQEDEJQ4Krh9jPrvkNYV2Lv5P3kDHqkeKUqfp",
      "chains": [
        "solana"
      ],
      "totalTokens": 3,
      "trackedTokens": 2,
      "wins": 1,
      "losses": 1,
      "winRate": 50,
      "avgReturn": -6.9,
      "score": 0,
      "firstSeen": 1773506911627,
      "topPicks": [
        {
          "symbol": "MERLIN",
          "chain": "solana",
          "change": 23.335016696188596
        },
        {
          "symbol": "ROSE",
          "chain": "solana",
          "change": -37.0389829257238
        }
      ]
    },
    {
      "address": "37TiV2MpnVgY6qJgDbGVkuKouKaab7UPpoXwtXKEuAfR",
      "chains": [
        "solana"
      ],
      "totalTokens": 2,
      "trackedTokens": 2,
      "wins": 1,
      "losses": 1,
      "winRate": 50,
      "avgReturn": -6.9,
      "score": 0,
      "firstSeen": 1773506911627,
      "topPicks": [
        {
          "symbol": "MERLIN",
          "chain": "solana",
          "change": 23.335016696188596
        },
        {
          "symbol": "ROSE",
          "chain": "solana",
          "change": -37.0389829257238
        }
      ]
    },
    {
      "address": "ELiQVfLbXQFJMd4qrBcDStMoTdvvRvzMNP5WWmtH38BJ",
      "chains": [
        "solana"
      ],
      "totalTokens": 3,
      "trackedTokens": 2,
      "wins": 0,
      "losses": 2,
      "winRate": 0,
      "avgReturn": -32.1,
      "score": 0,
      "firstSeen": 1773506911627,
      "topPicks": [
        {
          "symbol": "SMITH",
          "chain": "solana",
          "change": -18.59305456737125
        },
        {
          "symbol": "01001000",
          "chain": "solana",
          "change": -45.684243328451245
        }
      ]
    },
    {
      "address": "Gm4hdm6DgptJ1H3ZUYryJTbdDWDY35S4cm2QSPhMQ4fh",
      "chains": [
        "solana"
      ],
      "totalTokens": 5,
      "trackedTokens": 4,
      "wins": 1,
      "losses": 3,
      "winRate": 25,
      "avgReturn": -28.3,
      "score": 0,
      "firstSeen": 1773506911627,
      "topPicks": [
        {
          "symbol": "TERAFAB",
          "chain": "solana",
          "change": 101.97536752769005
        },
        {
          "symbol": "NORWOOD",
          "chain": "solana",
          "change": -45.34398205697774
        },
        {
          "symbol": "AI",
          "chain": "solana",
          "change": -78.20672337114156
        },
        {
          "symbol": "ZEZE",
          "chain": "solana",
          "change": -91.57332302783125
        }
      ]
    },
    {
      "address": "72NWWbchKdRJKvhG6U4f9363psUttkeEkE4yk15imy8u",
      "chains": [
        "solana"
      ],
      "totalTokens": 10,
      "trackedTokens": 4,
      "wins": 0,
      "losses": 4,
      "winRate": 0,
      "avgReturn": -17.1,
      "score": 0,
      "firstSeen": 1773506911627,
      "topPicks": [
        {
          "symbol": "WENDYS",
          "chain": "solana",
          "change": -1.4842468137427312
        },
        {
          "symbol": "Memehouse",
          "chain": "solana",
          "change": -2.59255500031965
        },
        {
          "symbol": "SMITH",
          "chain": "solana",
          "change": -18.59305456737125
        },
        {
          "symbol": "01001000",
          "chain": "solana",
          "change": -45.684243328451245
        }
      ]
    },
    {
      "address": "6NC63WahHimrn3UzWmqWd6qCrmhgKHfhLfXmjwR2kWZc",
      "chains": [
        "solana"
      ],
      "totalTokens": 6,
      "trackedTokens": 3,
      "wins": 0,
      "losses": 3,
      "winRate": 0,
      "avgReturn": -24.4,
      "score": 0,
      "firstSeen": 1773506911627,
      "topPicks": [
        {
          "symbol": "Memehouse",
          "chain": "solana",
          "change": -2.59255500031965
        },
        {
          "symbol": "SMITH",
          "chain": "solana",
          "change": -18.59305456737125
        },
        {
          "symbol": "$2",
          "chain": "solana",
          "change": -51.880307773174074
        }
      ]
    },
    {
      "address": "F1m5PSaeH9XPesLAmcv3rJaxkevEt7HJ1Puy6Ttb7JAL",
      "chains": [
        "solana"
      ],
      "totalTokens": 8,
      "trackedTokens": 5,
      "wins": 0,
      "losses": 5,
      "winRate": 0,
      "avgReturn": -24,
      "score": 0,
      "firstSeen": 1773506911627,
      "topPicks": [
        {
          "symbol": "WENDYS",
          "chain": "solana",
          "change": -1.4842468137427312
        },
        {
          "symbol": "Memehouse",
          "chain": "solana",
          "change": -2.59255500031965
        },
        {
          "symbol": "SMITH",
          "chain": "solana",
          "change": -18.59305456737125
        },
        {
          "symbol": "01001000",
          "chain": "solana",
          "change": -45.684243328451245
        },
        {
          "symbol": "$2",
          "chain": "solana",
          "change": -51.880307773174074
        }
      ]
    },
    {
      "address": "4tBE6E7ULJXuwH7Lqyy7pJHCQdoniMHD2R4GeXMGmX6W",
      "chains": [
        "solana"
      ],
      "totalTokens": 12,
      "trackedTokens": 5,
      "wins": 0,
      "losses": 5,
      "winRate": 0,
      "avgReturn": -24,
      "score": 0,
      "firstSeen": 1773506911627,
      "topPicks": [
        {
          "symbol": "WENDYS",
          "chain": "solana",
          "change": -1.4842468137427312
        },
        {
          "symbol": "Memehouse",
          "chain": "solana",
          "change": -2.59255500031965
        },
        {
          "symbol": "SMITH",
          "chain": "solana",
          "change": -18.59305456737125
        },
        {
          "symbol": "01001000",
          "chain": "solana",
          "change": -45.684243328451245
        },
        {
          "symbol": "$2",
          "chain": "solana",
          "change": -51.880307773174074
        }
      ]
    },
    {
      "address": "ADPCcUUS2qmSFtAgxiJMCVsk6WeoS1ux4QF8aJJeW78d",
      "chains": [
        "solana"
      ],
      "totalTokens": 7,
      "trackedTokens": 3,
      "wins": 0,
      "losses": 3,
      "winRate": 0,
      "avgReturn": -38.7,
      "score": 0,
      "firstSeen": 1773506911627,
      "topPicks": [
        {
          "symbol": "SMITH",
          "chain": "solana",
          "change": -18.59305456737125
        },
        {
          "symbol": "01001000",
          "chain": "solana",
          "change": -45.684243328451245
        },
        {
          "symbol": "$2",
          "chain": "solana",
          "change": -51.880307773174074
        }
      ]
    },
    {
      "address": "BtW2Dh7ACiPi9yMkuiz2L8FS4MvuE9scyUWFwne3Mamm",
      "chains": [
        "solana"
      ],
      "totalTokens": 5,
      "trackedTokens": 3,
      "wins": 1,
      "losses": 2,
      "winRate": 33.3,
      "avgReturn": -21.2,
      "score": 0,
      "firstSeen": 1773506911627,
      "topPicks": [
        {
          "symbol": "Life",
          "chain": "solana",
          "change": 0.3626411156351229
        },
        {
          "symbol": "SMITH",
          "chain": "solana",
          "change": -18.59305456737125
        },
        {
          "symbol": "NORWOOD",
          "chain": "solana",
          "change": -45.34398205697774
        }
      ]
    },
    {
      "address": "71pAfN1nJhcLaezSRYvwdsNFE9PnY9hNfcxB4nZ1gdAp",
      "chains": [
        "solana"
      ],
      "totalTokens": 6,
      "trackedTokens": 3,
      "wins": 0,
      "losses": 3,
      "winRate": 0,
      "avgReturn": -38.7,
      "score": 0,
      "firstSeen": 1773506911627,
      "topPicks": [
        {
          "symbol": "SMITH",
          "chain": "solana",
          "change": -18.59305456737125
        },
        {
          "symbol": "01001000",
          "chain": "solana",
          "change": -45.684243328451245
        },
        {
          "symbol": "$2",
          "chain": "solana",
          "change": -51.880307773174074
        }
      ]
    },
    {
      "address": "6kzsXq32zgmW1cEw9xKn9HyfE72oUX9b8PiPBZ8fWn9S",
      "chains": [
        "solana"
      ],
      "totalTokens": 5,
      "trackedTokens": 3,
      "wins": 1,
      "losses": 2,
      "winRate": 33.3,
      "avgReturn": -6.9,
      "score": 0,
      "firstSeen": 1773506911627,
      "topPicks": [
        {
          "symbol": "Life",
          "chain": "solana",
          "change": 0.3626411156351229
        },
        {
          "symbol": "Memehouse",
          "chain": "solana",
          "change": -2.59255500031965
        },
        {
          "symbol": "SMITH",
          "chain": "solana",
          "change": -18.59305456737125
        }
      ]
    },
    {
      "address": "21xsLyMB5v9hryZFL6S2sk5GfKwRfWuisV9ucMYhNWML",
      "chains": [
        "solana"
      ],
      "totalTokens": 2,
      "trackedTokens": 2,
      "wins": 0,
      "losses": 2,
      "winRate": 0,
      "avgReturn": -10,
      "score": 0,
      "firstSeen": 1773506911627,
      "topPicks": [
        {
          "symbol": "WENDYS",
          "chain": "solana",
          "change": -1.4842468137427312
        },
        {
          "symbol": "SMITH",
          "chain": "solana",
          "change": -18.59305456737125
        }
      ]
    },
    {
      "address": "Ca9JD3UbaT86TxmbHa9SGYm8FxwSffr4c2Y2viHyUXYf",
      "chains": [
        "solana"
      ],
      "totalTokens": 2,
      "trackedTokens": 2,
      "wins": 0,
      "losses": 2,
      "winRate": 0,
      "avgReturn": -91.3,
      "score": 0,
      "firstSeen": 1773506911627,
      "topPicks": [
        {
          "symbol": "Gojo",
          "chain": "solana",
          "change": -89.67866331013477
        },
        {
          "symbol": "BOTTOM",
          "chain": "solana",
          "change": -92.86542618384131
        }
      ]
    },
    {
      "address": "5ruPgyUP4Y7WbTBMeF1RMDcfrpY26DegMWVTbiFzobAP",
      "chains": [
        "solana"
      ],
      "totalTokens": 3,
      "trackedTokens": 2,
      "wins": 0,
      "losses": 2,
      "winRate": 0,
      "avgReturn": -10,
      "score": 0,
      "firstSeen": 1773506911627,
      "topPicks": [
        {
          "symbol": "WENDYS",
          "chain": "solana",
          "change": -1.4842468137427312
        },
        {
          "symbol": "SMITH",
          "chain": "solana",
          "change": -18.59305456737125
        }
      ]
    },
    {
      "address": "8Fb1HWGpyopD3oE4QT4ocAMiPxVsT2QDcn9XqTsuJdSo",
      "chains": [
        "solana"
      ],
      "totalTokens": 6,
      "trackedTokens": 4,
      "wins": 0,
      "losses": 4,
      "winRate": 0,
      "avgReturn": -56.5,
      "score": 0,
      "firstSeen": 1773506911627,
      "topPicks": [
        {
          "symbol": "WENDYS",
          "chain": "solana",
          "change": -1.4842468137427312
        },
        {
          "symbol": "Slop",
          "chain": "solana",
          "change": -39.52922514415743
        },
        {
          "symbol": "Limitless",
          "chain": "solana",
          "change": -90.0955479115884
        },
        {
          "symbol": "Next",
          "chain": "solana",
          "change": -94.80068647347618
        }
      ]
    },
    {
      "address": "HGfjZWjJxy12hXZXv3uUEk2iruMAf6pbAtXYQv4Qujhy",
      "chains": [
        "solana"
      ],
      "totalTokens": 4,
      "trackedTokens": 3,
      "wins": 0,
      "losses": 3,
      "winRate": 0,
      "avgReturn": -60.4,
      "score": 0,
      "firstSeen": 1773506911628,
      "topPicks": [
        {
          "symbol": "WENDYS",
          "chain": "solana",
          "change": -1.4842468137427312
        },
        {
          "symbol": "Gojo",
          "chain": "solana",
          "change": -89.67866331013477
        },
        {
          "symbol": "Limitless",
          "chain": "solana",
          "change": -90.0955479115884
        }
      ]
    },
    {
      "address": "61oYiwNbd56CD653K8saGz1WDNRsLdsXTfex8SxYVmJe",
      "chains": [
        "solana"
      ],
      "totalTokens": 2,
      "trackedTokens": 2,
      "wins": 0,
      "losses": 2,
      "winRate": 0,
      "avgReturn": -48.3,
      "score": 0,
      "firstSeen": 1773506911628,
      "topPicks": [
        {
          "symbol": "HORSES",
          "chain": "solana",
          "change": -6.905944064051963
        },
        {
          "symbol": "Gojo",
          "chain": "solana",
          "change": -89.67866331013477
        }
      ]
    },
    {
      "address": "66X7sbbEeQKg4KyQGBF5skPAUccpi2X2Upmrsd3zUCUA",
      "chains": [
        "solana"
      ],
      "totalTokens": 2,
      "trackedTokens": 2,
      "wins": 0,
      "losses": 2,
      "winRate": 0,
      "avgReturn": -84.8,
      "score": 0,
      "firstSeen": 1773506911628,
      "topPicks": [
        {
          "symbol": "SMORT",
          "chain": "solana",
          "change": -79.86341698092924
        },
        {
          "symbol": "Gojo",
          "chain": "solana",
          "change": -89.67866331013477
        }
      ]
    },
    {
      "address": "9nP8diLFigo1wmWxg2R1k4JEHnmw6MtUvmeDudVfwpE6",
      "chains": [
        "solana"
      ],
      "totalTokens": 2,
      "trackedTokens": 2,
      "wins": 0,
      "losses": 2,
      "winRate": 0,
      "avgReturn": -45.1,
      "score": 0,
      "firstSeen": 1773506911628,
      "topPicks": [
        {
          "symbol": "WENDYS",
          "chain": "solana",
          "change": -1.4842468137427312
        },
        {
          "symbol": "X COINS",
          "chain": "solana",
          "change": -88.65825919408314
        }
      ]
    },
    {
      "address": "F39m9XpuE9s44QHWEf2YSvukoy564oAqQrzgM68YjRPA",
      "chains": [
        "solana"
      ],
      "totalTokens": 3,
      "trackedTokens": 2,
      "wins": 0,
      "losses": 2,
      "winRate": 0,
      "avgReturn": -45.8,
      "score": 0,
      "firstSeen": 1773506911628,
      "topPicks": [
        {
          "symbol": "WENDYS",
          "chain": "solana",
          "change": -1.4842468137427312
        },
        {
          "symbol": "Limitless",
          "chain": "solana",
          "change": -90.0955479115884
        }
      ]
    },
    {
      "address": "0xa17791bfcc6030e6e5c0d6528fc6253f76e93f59",
      "chains": [
        "bsc"
      ],
      "totalTokens": 11,
      "trackedTokens": 8,
      "wins": 0,
      "losses": 8,
      "winRate": 0,
      "avgReturn": -92.8,
      "score": 0,
      "firstSeen": 1773506911853,
      "topPicks": [
        {
          "symbol": "波龙",
          "chain": "bsc",
          "change": -77.83415715079039
        },
        {
          "symbol": "元",
          "chain": "bsc",
          "change": -85.01734602636067
        },
        {
          "symbol": "币安青蛙",
          "chain": "bsc",
          "change": -92.42140860793597
        },
        {
          "symbol": "波龙",
          "chain": "bsc",
          "change": -97.04869173005515
        },
        {
          "symbol": "波龙",
          "chain": "bsc",
          "change": -97.37666089303639
        }
      ]
    },
    {
      "address": "0x0f80aa9dd2aff0d79455a1f7843c6e39e5a27985",
      "chains": [
        "bsc"
      ],
      "totalTokens": 11,
      "trackedTokens": 8,
      "wins": 0,
      "losses": 8,
      "winRate": 0,
      "avgReturn": -92.8,
      "score": 0,
      "firstSeen": 1773506911853,
      "topPicks": [
        {
          "symbol": "波龙",
          "chain": "bsc",
          "change": -77.83415715079039
        },
        {
          "symbol": "元",
          "chain": "bsc",
          "change": -85.01734602636067
        },
        {
          "symbol": "币安青蛙",
          "chain": "bsc",
          "change": -92.42140860793597
        },
        {
          "symbol": "波龙",
          "chain": "bsc",
          "change": -97.04869173005515
        },
        {
          "symbol": "波龙",
          "chain": "bsc",
          "change": -97.37666089303639
        }
      ]
    },
    {
      "address": "0xdb71bdeca66fd0659f6cac5035d357f981f3bd96",
      "chains": [
        "bsc"
      ],
      "totalTokens": 2,
      "trackedTokens": 2,
      "wins": 0,
      "losses": 2,
      "winRate": 0,
      "avgReturn": -85.8,
      "score": 0,
      "firstSeen": 1773506911853,
      "topPicks": [
        {
          "symbol": "MoonCat",
          "chain": "bsc",
          "change": -79.21905671128339
        },
        {
          "symbol": "币安青蛙",
          "chain": "bsc",
          "change": -92.42140860793597
        }
      ]
    },
    {
      "address": "0xe5bc72e5f9619f3c001c5081be55cf98f0d44860",
      "chains": [
        "bsc"
      ],
      "totalTokens": 3,
      "trackedTokens": 3,
      "wins": 0,
      "losses": 3,
      "winRate": 0,
      "avgReturn": -30.7,
      "score": 0,
      "firstSeen": 1773506911853,
      "topPicks": [
        {
          "symbol": "Fight",
          "chain": "bsc",
          "change": -2.519284602892678
        },
        {
          "symbol": "MOONDOGE",
          "chain": "bsc",
          "change": -4.47212373066357
        },
        {
          "symbol": "元",
          "chain": "bsc",
          "change": -85.01734602636067
        }
      ]
    },
    {
      "address": "0xf98ab9fe84bf564b3de827fc9e3bacddc3122679",
      "chains": [
        "bsc"
      ],
      "totalTokens": 5,
      "trackedTokens": 3,
      "wins": 0,
      "losses": 3,
      "winRate": 0,
      "avgReturn": -73.9,
      "score": 0,
      "firstSeen": 1773506911853,
      "topPicks": [
        {
          "symbol": "天梯",
          "chain": "bsc",
          "change": -25.93572786343937
        },
        {
          "symbol": "天梯",
          "chain": "bsc",
          "change": -97.76657338463744
        },
        {
          "symbol": "Elon musk",
          "chain": "bsc",
          "change": -98.05949730979835
        }
      ]
    },
    {
      "address": "0xd029a6eba27862c520001b85981432dd84465c4c",
      "chains": [
        "bsc"
      ],
      "totalTokens": 5,
      "trackedTokens": 5,
      "wins": 2,
      "losses": 3,
      "winRate": 40,
      "avgReturn": -20.1,
      "score": 0,
      "firstSeen": 1773506911854,
      "topPicks": [
        {
          "symbol": "小龙虾",
          "chain": "bsc",
          "change": 52.890603262128266
        },
        {
          "symbol": "WUKONG",
          "chain": "bsc",
          "change": 11.30493991265331
        },
        {
          "symbol": "天梯",
          "chain": "bsc",
          "change": -25.93572786343937
        },
        {
          "symbol": "Punch",
          "chain": "bsc",
          "change": -39.03645378646841
        },
        {
          "symbol": "BSN",
          "chain": "bsc",
          "change": -99.72198307718091
        }
      ]
    },
    {
      "address": "0x9cace25529d4d1682325ecd6a67a757ecfd1d9be",
      "chains": [
        "bsc"
      ],
      "totalTokens": 3,
      "trackedTokens": 3,
      "wins": 0,
      "losses": 3,
      "winRate": 0,
      "avgReturn": -72.6,
      "score": 0,
      "firstSeen": 1773506911854,
      "topPicks": [
        {
          "symbol": "Punch",
          "chain": "bsc",
          "change": -39.03645378646841
        },
        {
          "symbol": "元",
          "chain": "bsc",
          "change": -85.01734602636067
        },
        {
          "symbol": "FAFO",
          "chain": "bsc",
          "change": -93.7211149521641
        }
      ]
    },
    {
      "address": "0xe92c26ddc8929a7c4360be4ccc0b99b7b4fbeb9b",
      "chains": [
        "bsc"
      ],
      "totalTokens": 3,
      "trackedTokens": 2,
      "wins": 0,
      "losses": 2,
      "winRate": 0,
      "avgReturn": -32.5,
      "score": 0,
      "firstSeen": 1773506911854,
      "topPicks": [
        {
          "symbol": "天梯",
          "chain": "bsc",
          "change": -25.93572786343937
        },
        {
          "symbol": "Punch",
          "chain": "bsc",
          "change": -39.03645378646841
        }
      ]
    },
    {
      "address": "0xe12a7999895c1b3c1589a8fa6db5cff39fd46cce",
      "chains": [
        "bsc"
      ],
      "totalTokens": 2,
      "trackedTokens": 2,
      "wins": 0,
      "losses": 2,
      "winRate": 0,
      "avgReturn": -66.4,
      "score": 0,
      "firstSeen": 1773506911854,
      "topPicks": [
        {
          "symbol": "Punch",
          "chain": "bsc",
          "change": -39.03645378646841
        },
        {
          "symbol": "FAFO",
          "chain": "bsc",
          "change": -93.7211149521641
        }
      ]
    },
    {
      "address": "0x6d2bf314202ede9c4eb74451aefd32900ec6c3df",
      "chains": [
        "bsc"
      ],
      "totalTokens": 5,
      "trackedTokens": 4,
      "wins": 0,
      "losses": 4,
      "winRate": 0,
      "avgReturn": -79.7,
      "score": 0,
      "firstSeen": 1773506911854,
      "topPicks": [
        {
          "symbol": "天梯",
          "chain": "bsc",
          "change": -25.93572786343937
        },
        {
          "symbol": "MemeClaw",
          "chain": "bsc",
          "change": -97.42605414472742
        },
        {
          "symbol": "MemeClaw",
          "chain": "bsc",
          "change": -97.5714915797616
        },
        {
          "symbol": "天梯",
          "chain": "bsc",
          "change": -97.76657338463744
        }
      ]
    },
    {
      "address": "0xa741d1090cb23d3da86e1f281353dee30e992f43",
      "chains": [
        "bsc"
      ],
      "totalTokens": 7,
      "trackedTokens": 6,
      "wins": 1,
      "losses": 5,
      "winRate": 16.7,
      "avgReturn": -67.4,
      "score": 0,
      "firstSeen": 1773506911854,
      "topPicks": [
        {
          "symbol": "WUKONG",
          "chain": "bsc",
          "change": 11.30493991265331
        },
        {
          "symbol": "天梯",
          "chain": "bsc",
          "change": -25.93572786343937
        },
        {
          "symbol": "波龙",
          "chain": "bsc",
          "change": -97.04869173005515
        },
        {
          "symbol": "波龙",
          "chain": "bsc",
          "change": -97.37666089303639
        },
        {
          "symbol": "MemeClaw",
          "chain": "bsc",
          "change": -97.42605414472742
        }
      ]
    },
    {
      "address": "0x770a9a0d1aee5c41052358ce32324fe33084279f",
      "chains": [
        "bsc"
      ],
      "totalTokens": 5,
      "trackedTokens": 4,
      "wins": 1,
      "losses": 3,
      "winRate": 25,
      "avgReturn": -37.2,
      "score": 0,
      "firstSeen": 1773506911854,
      "topPicks": [
        {
          "symbol": "小龙虾",
          "chain": "bsc",
          "change": 52.890603262128266
        },
        {
          "symbol": "天梯",
          "chain": "bsc",
          "change": -25.93572786343937
        },
        {
          "symbol": "波龙",
          "chain": "bsc",
          "change": -77.83415715079039
        },
        {
          "symbol": "天梯",
          "chain": "bsc",
          "change": -97.76657338463744
        }
      ]
    },
    {
      "address": "0xdc07ddadd60141013e2c2b6d1acb04cd9d1d689a",
      "chains": [
        "bsc"
      ],
      "totalTokens": 4,
      "trackedTokens": 3,
      "wins": 0,
      "losses": 3,
      "winRate": 0,
      "avgReturn": -73.8,
      "score": 0,
      "firstSeen": 1773506911854,
      "topPicks": [
        {
          "symbol": "天梯",
          "chain": "bsc",
          "change": -25.93572786343937
        },
        {
          "symbol": "MemeClaw",
          "chain": "bsc",
          "change": -97.5714915797616
        },
        {
          "symbol": "天梯",
          "chain": "bsc",
          "change": -97.76657338463744
        }
      ]
    },
    {
      "address": "0x6699e6541c55a6e1c44793858d6ddad217583d78",
      "chains": [
        "bsc"
      ],
      "totalTokens": 2,
      "trackedTokens": 2,
      "wins": 0,
      "losses": 2,
      "winRate": 0,
      "avgReturn": -61.7,
      "score": 0,
      "firstSeen": 1773506911854,
      "topPicks": [
        {
          "symbol": "天梯",
          "chain": "bsc",
          "change": -25.93572786343937
        },
        {
          "symbol": "MemeClaw",
          "chain": "bsc",
          "change": -97.42605414472742
        }
      ]
    },
    {
      "address": "0x2cd73f100bf38d986c950ad6a7d36d58c73d6886",
      "chains": [
        "bsc"
      ],
      "totalTokens": 5,
      "trackedTokens": 5,
      "wins": 0,
      "losses": 5,
      "winRate": 0,
      "avgReturn": -79.2,
      "score": 0,
      "firstSeen": 1773506911854,
      "topPicks": [
        {
          "symbol": "天梯",
          "chain": "bsc",
          "change": -25.93572786343937
        },
        {
          "symbol": "波龙",
          "chain": "bsc",
          "change": -77.83415715079039
        },
        {
          "symbol": "波龙",
          "chain": "bsc",
          "change": -97.04869173005515
        },
        {
          "symbol": "波龙",
          "chain": "bsc",
          "change": -97.37666089303639
        },
        {
          "symbol": "天梯",
          "chain": "bsc",
          "change": -97.76657338463744
        }
      ]
    },
    {
      "address": "0xcddae7f7bae3df5640ded1832d50d1345b7541f9",
      "chains": [
        "bsc"
      ],
      "totalTokens": 5,
      "trackedTokens": 5,
      "wins": 1,
      "losses": 4,
      "winRate": 20,
      "avgReturn": -58,
      "score": 0,
      "firstSeen": 1773506911854,
      "topPicks": [
        {
          "symbol": "WUKONG",
          "chain": "bsc",
          "change": 11.30493991265331
        },
        {
          "symbol": "天梯",
          "chain": "bsc",
          "change": -25.93572786343937
        },
        {
          "symbol": "波龙",
          "chain": "bsc",
          "change": -77.83415715079039
        },
        {
          "symbol": "天梯",
          "chain": "bsc",
          "change": -97.76657338463744
        },
        {
          "symbol": "BSN",
          "chain": "bsc",
          "change": -99.72198307718091
        }
      ]
    },
    {
      "address": "0xd89e91754a6a5fe8ccdf725df233a15ed6ce25a5",
      "chains": [
        "bsc"
      ],
      "totalTokens": 4,
      "trackedTokens": 4,
      "wins": 2,
      "losses": 2,
      "winRate": 50,
      "avgReturn": -9.9,
      "score": 0,
      "firstSeen": 1773506911854,
      "topPicks": [
        {
          "symbol": "小龙虾",
          "chain": "bsc",
          "change": 52.890603262128266
        },
        {
          "symbol": "WUKONG",
          "chain": "bsc",
          "change": 11.30493991265331
        },
        {
          "symbol": "天梯",
          "chain": "bsc",
          "change": -25.93572786343937
        },
        {
          "symbol": "波龙",
          "chain": "bsc",
          "change": -77.83415715079039
        }
      ]
    },
    {
      "address": "0xe400affc23a2f956fdd4c53281be708de3f403a9",
      "chains": [
        "bsc"
      ],
      "totalTokens": 7,
      "trackedTokens": 7,
      "wins": 2,
      "losses": 5,
      "winRate": 28.6,
      "avgReturn": -47.4,
      "score": 0,
      "firstSeen": 1773506911854,
      "topPicks": [
        {
          "symbol": "小龙虾",
          "chain": "bsc",
          "change": 52.890603262128266
        },
        {
          "symbol": "WUKONG",
          "chain": "bsc",
          "change": 11.30493991265331
        },
        {
          "symbol": "天梯",
          "chain": "bsc",
          "change": -25.93572786343937
        },
        {
          "symbol": "波龙",
          "chain": "bsc",
          "change": -77.83415715079039
        },
        {
          "symbol": "波龙",
          "chain": "bsc",
          "change": -97.04869173005515
        }
      ]
    },
    {
      "address": "0xba7f6610c538cba87395f995e74ba69114521f27",
      "chains": [
        "bsc"
      ],
      "totalTokens": 2,
      "trackedTokens": 2,
      "wins": 0,
      "losses": 2,
      "winRate": 0,
      "avgReturn": -62.8,
      "score": 0,
      "firstSeen": 1773506911854,
      "topPicks": [
        {
          "symbol": "天梯",
          "chain": "bsc",
          "change": -25.93572786343937
        },
        {
          "symbol": "BSN",
          "chain": "bsc",
          "change": -99.72198307718091
        }
      ]
    },
    {
      "address": "0x90849db5afdee8085cd9a9814991531a903d2be4",
      "chains": [
        "bsc"
      ],
      "totalTokens": 2,
      "trackedTokens": 2,
      "wins": 0,
      "losses": 2,
      "winRate": 0,
      "avgReturn": -61.9,
      "score": 0,
      "firstSeen": 1773506911854,
      "topPicks": [
        {
          "symbol": "天梯",
          "chain": "bsc",
          "change": -25.93572786343937
        },
        {
          "symbol": "天梯",
          "chain": "bsc",
          "change": -97.76657338463744
        }
      ]
    },
    {
      "address": "0x261c2fbb29e99776795482a6de004ee3cc3ee504",
      "chains": [
        "bsc"
      ],
      "totalTokens": 2,
      "trackedTokens": 2,
      "wins": 0,
      "losses": 2,
      "winRate": 0,
      "avgReturn": -61.9,
      "score": 0,
      "firstSeen": 1773506911854,
      "topPicks": [
        {
          "symbol": "天梯",
          "chain": "bsc",
          "change": -25.93572786343937
        },
        {
          "symbol": "天梯",
          "chain": "bsc",
          "change": -97.76657338463744
        }
      ]
    },
    {
      "address": "0xd38e1bc6ee966a11d5b2550063927731079d612e",
      "chains": [
        "bsc"
      ],
      "totalTokens": 2,
      "trackedTokens": 2,
      "wins": 0,
      "losses": 2,
      "winRate": 0,
      "avgReturn": -61.9,
      "score": 0,
      "firstSeen": 1773506911854,
      "topPicks": [
        {
          "symbol": "天梯",
          "chain": "bsc",
          "change": -25.93572786343937
        },
        {
          "symbol": "天梯",
          "chain": "bsc",
          "change": -97.76657338463744
        }
      ]
    },
    {
      "address": "0x6390254ce318c7f57c1e8f243cfc72b3034dd737",
      "chains": [
        "bsc"
      ],
      "totalTokens": 2,
      "trackedTokens": 2,
      "wins": 0,
      "losses": 2,
      "winRate": 0,
      "avgReturn": -61.9,
      "score": 0,
      "firstSeen": 1773506911854,
      "topPicks": [
        {
          "symbol": "天梯",
          "chain": "bsc",
          "change": -25.93572786343937
        },
        {
          "symbol": "天梯",
          "chain": "bsc",
          "change": -97.76657338463744
        }
      ]
    },
    {
      "address": "0x66ef7aedb139468ef75ba1eb97e1430ca28de29e",
      "chains": [
        "bsc"
      ],
      "totalTokens": 2,
      "trackedTokens": 2,
      "wins": 0,
      "losses": 2,
      "winRate": 0,
      "avgReturn": -61.7,
      "score": 0,
      "firstSeen": 1773506911854,
      "topPicks": [
        {
          "symbol": "天梯",
          "chain": "bsc",
          "change": -25.93572786343937
        },
        {
          "symbol": "波龙",
          "chain": "bsc",
          "change": -97.37666089303639
        }
      ]
    },
    {
      "address": "0x396425e40596dcbb59576fd606db27bdee77f933",
      "chains": [
        "bsc"
      ],
      "totalTokens": 3,
      "trackedTokens": 2,
      "wins": 0,
      "losses": 2,
      "winRate": 0,
      "avgReturn": -59.8,
      "score": 0,
      "firstSeen": 1773506911854,
      "topPicks": [
        {
          "symbol": "天梯",
          "chain": "bsc",
          "change": -25.93572786343937
        },
        {
          "symbol": "FAFO",
          "chain": "bsc",
          "change": -93.7211149521641
        }
      ]
    },
    {
      "address": "0xd7956b9ed49a95b1d3524bfe0da8625cc02aa1b1",
      "chains": [
        "bsc"
      ],
      "totalTokens": 5,
      "trackedTokens": 5,
      "wins": 2,
      "losses": 3,
      "winRate": 40,
      "avgReturn": -31.7,
      "score": 0,
      "firstSeen": 1773506911854,
      "topPicks": [
        {
          "symbol": "小龙虾",
          "chain": "bsc",
          "change": 52.890603262128266
        },
        {
          "symbol": "WUKONG",
          "chain": "bsc",
          "change": 11.30493991265331
        },
        {
          "symbol": "天梯",
          "chain": "bsc",
          "change": -25.93572786343937
        },
        {
          "symbol": "波龙",
          "chain": "bsc",
          "change": -97.04869173005515
        },
        {
          "symbol": "BSN",
          "chain": "bsc",
          "change": -99.72198307718091
        }
      ]
    },
    {
      "address": "0x27574268800a7cf72a750a13df8730c9dfe956b4",
      "chains": [
        "bsc"
      ],
      "totalTokens": 3,
      "trackedTokens": 3,
      "wins": 0,
      "losses": 3,
      "winRate": 0,
      "avgReturn": -47,
      "score": 0,
      "firstSeen": 1773506911854,
      "topPicks": [
        {
          "symbol": "小安助手",
          "chain": "bsc",
          "change": -21.209041511463294
        },
        {
          "symbol": "天梯",
          "chain": "bsc",
          "change": -25.93572786343937
        },
        {
          "symbol": "FAFO",
          "chain": "bsc",
          "change": -93.7211149521641
        }
      ]
    },
    {
      "address": "0x71fc8104d5cab689c0c8a1eea668ed840e8143d5",
      "chains": [
        "bsc"
      ],
      "totalTokens": 4,
      "trackedTokens": 4,
      "wins": 0,
      "losses": 4,
      "winRate": 0,
      "avgReturn": -51.8,
      "score": 0,
      "firstSeen": 1773506911854,
      "topPicks": [
        {
          "symbol": "天梯",
          "chain": "bsc",
          "change": -25.93572786343937
        },
        {
          "symbol": "Memehouse",
          "chain": "bsc",
          "change": -50.80982894219438
        },
        {
          "symbol": "川普",
          "chain": "bsc",
          "change": -53.496967289353655
        },
        {
          "symbol": "Memrush",
          "chain": "bsc",
          "change": -77.04969422632857
        }
      ]
    },
    {
      "address": "0x789fc3e3deb5c36ca7020f015f07b46cf9c808e0",
      "chains": [
        "bsc"
      ],
      "totalTokens": 3,
      "trackedTokens": 3,
      "wins": 0,
      "losses": 3,
      "winRate": 0,
      "avgReturn": -48.3,
      "score": 0,
      "firstSeen": 1773506911854,
      "topPicks": [
        {
          "symbol": "小安助手",
          "chain": "bsc",
          "change": -21.209041511463294
        },
        {
          "symbol": "天梯",
          "chain": "bsc",
          "change": -25.93572786343937
        },
        {
          "symbol": "天梯",
          "chain": "bsc",
          "change": -97.76657338463744
        }
      ]
    },
    {
      "address": "0xf8117ee3c279e2a717fdecc204b6236fd56a3cb3",
      "chains": [
        "bsc"
      ],
      "totalTokens": 5,
      "trackedTokens": 5,
      "wins": 1,
      "losses": 4,
      "winRate": 20,
      "avgReturn": -27.6,
      "score": 0,
      "firstSeen": 1773506911854,
      "topPicks": [
        {
          "symbol": "WUKONG",
          "chain": "bsc",
          "change": 11.30493991265331
        },
        {
          "symbol": "MOONDOGE",
          "chain": "bsc",
          "change": -4.47212373066357
        },
        {
          "symbol": "小安助手",
          "chain": "bsc",
          "change": -21.209041511463294
        },
        {
          "symbol": "天梯",
          "chain": "bsc",
          "change": -25.93572786343937
        },
        {
          "symbol": "天梯",
          "chain": "bsc",
          "change": -97.76657338463744
        }
      ]
    },
    {
      "address": "0x9e74cf67751a9b3d445ec297adbad5fb58bdbe6f",
      "chains": [
        "bsc"
      ],
      "totalTokens": 2,
      "trackedTokens": 2,
      "wins": 0,
      "losses": 2,
      "winRate": 0,
      "avgReturn": -42.8,
      "score": 0,
      "firstSeen": 1773506911854,
      "topPicks": [
        {
          "symbol": "天梯",
          "chain": "bsc",
          "change": -25.93572786343937
        },
        {
          "symbol": "OPC",
          "chain": "bsc",
          "change": -59.66241790414356
        }
      ]
    },
    {
      "address": "0xfe0e113120d81e8b3b816bafd27eba3932ec8cbf",
      "chains": [
        "bsc"
      ],
      "totalTokens": 2,
      "trackedTokens": 2,
      "wins": 0,
      "losses": 2,
      "winRate": 0,
      "avgReturn": -51.9,
      "score": 0,
      "firstSeen": 1773506911854,
      "topPicks": [
        {
          "symbol": "天梯",
          "chain": "bsc",
          "change": -25.93572786343937
        },
        {
          "symbol": "波龙",
          "chain": "bsc",
          "change": -77.83415715079039
        }
      ]
    },
    {
      "address": "0x06b1b315d684e0557d524986a8a9aba4906094f0",
      "chains": [
        "bsc"
      ],
      "totalTokens": 7,
      "trackedTokens": 7,
      "wins": 1,
      "losses": 6,
      "winRate": 14.3,
      "avgReturn": -79.2,
      "score": 0,
      "firstSeen": 1773506911854,
      "topPicks": [
        {
          "symbol": "WUKONG",
          "chain": "bsc",
          "change": 11.30493991265331
        },
        {
          "symbol": "波龙",
          "chain": "bsc",
          "change": -77.83415715079039
        },
        {
          "symbol": "波龙",
          "chain": "bsc",
          "change": -97.04869173005515
        },
        {
          "symbol": "波龙",
          "chain": "bsc",
          "change": -97.37666089303639
        },
        {
          "symbol": "MemeClaw",
          "chain": "bsc",
          "change": -97.42605414472742
        }
      ]
    },
    {
      "address": "0x68272a2392a7c29de511146dd5c538eef35dbcba",
      "chains": [
        "bsc"
      ],
      "totalTokens": 2,
      "trackedTokens": 2,
      "wins": 0,
      "losses": 2,
      "winRate": 0,
      "avgReturn": -96,
      "score": 0,
      "firstSeen": 1773506911854,
      "topPicks": [
        {
          "symbol": "无主之币",
          "chain": "bsc",
          "change": -92.24554571396854
        },
        {
          "symbol": "BSN",
          "chain": "bsc",
          "change": -99.72198307718091
        }
      ]
    },
    {
      "address": "0x6e960ba6e0fb3d0da9f6be603a777b5dcca93d63",
      "chains": [
        "bsc"
      ],
      "totalTokens": 2,
      "trackedTokens": 2,
      "wins": 0,
      "losses": 2,
      "winRate": 0,
      "avgReturn": -36,
      "score": 0,
      "firstSeen": 1773506911854,
      "topPicks": [
        {
          "symbol": "小安助手",
          "chain": "bsc",
          "change": -21.209041511463294
        },
        {
          "symbol": "Memehouse",
          "chain": "bsc",
          "change": -50.80982894219438
        }
      ]
    },
    {
      "address": "0x17f381b62025bbfcd57ce39c765f2cc44f1c2208",
      "chains": [
        "bsc"
      ],
      "totalTokens": 2,
      "trackedTokens": 2,
      "wins": 0,
      "losses": 2,
      "winRate": 0,
      "avgReturn": -97.7,
      "score": 0,
      "firstSeen": 1773506911854,
      "topPicks": [
        {
          "symbol": "MemeClaw",
          "chain": "bsc",
          "change": -97.42605414472742
        },
        {
          "symbol": "Elon musk",
          "chain": "bsc",
          "change": -98.05949730979835
        }
      ]
    },
    {
      "address": "0x3f9f5b18cad7a090717f27b497ffd348a5f116c5",
      "chains": [
        "bsc"
      ],
      "totalTokens": 2,
      "trackedTokens": 2,
      "wins": 0,
      "losses": 2,
      "winRate": 0,
      "avgReturn": -97.7,
      "score": 0,
      "firstSeen": 1773506911854,
      "topPicks": [
        {
          "symbol": "MemeClaw",
          "chain": "bsc",
          "change": -97.42605414472742
        },
        {
          "symbol": "Elon musk",
          "chain": "bsc",
          "change": -98.05949730979835
        }
      ]
    },
    {
      "address": "0x7e6b3dff057d809c5246aaad93e7678bcdc2c1d0",
      "chains": [
        "bsc"
      ],
      "totalTokens": 2,
      "trackedTokens": 2,
      "wins": 0,
      "losses": 2,
      "winRate": 0,
      "avgReturn": -97.7,
      "score": 0,
      "firstSeen": 1773506911854,
      "topPicks": [
        {
          "symbol": "MemeClaw",
          "chain": "bsc",
          "change": -97.42605414472742
        },
        {
          "symbol": "Elon musk",
          "chain": "bsc",
          "change": -98.05949730979835
        }
      ]
    },
    {
      "address": "0x15a0079924051b77315ec2c12d0f3605cad8969c",
      "chains": [
        "bsc"
      ],
      "totalTokens": 9,
      "trackedTokens": 9,
      "wins": 2,
      "losses": 7,
      "winRate": 22.2,
      "avgReturn": -66.1,
      "score": 0,
      "firstSeen": 1773506911854,
      "topPicks": [
        {
          "symbol": "小龙虾",
          "chain": "bsc",
          "change": 52.890603262128266
        },
        {
          "symbol": "WUKONG",
          "chain": "bsc",
          "change": 11.30493991265331
        },
        {
          "symbol": "波龙",
          "chain": "bsc",
          "change": -77.83415715079039
        },
        {
          "symbol": "FAFO",
          "chain": "bsc",
          "change": -93.7211149521641
        },
        {
          "symbol": "波龙",
          "chain": "bsc",
          "change": -97.04869173005515
        }
      ]
    },
    {
      "address": "0x47b051a56b1ad7fe0a4d0fda5dc8ee72243e3da8",
      "chains": [
        "bsc"
      ],
      "totalTokens": 2,
      "trackedTokens": 2,
      "wins": 0,
      "losses": 2,
      "winRate": 0,
      "avgReturn": -89,
      "score": 0,
      "firstSeen": 1773506911854,
      "topPicks": [
        {
          "symbol": "元",
          "chain": "bsc",
          "change": -85.01734602636067
        },
        {
          "symbol": "Meme Strategy",
          "chain": "bsc",
          "change": -92.9605455737161
        }
      ]
    },
    {
      "address": "0x85f5f5a617ae030eb6341d04b79ecf9c6eb33205",
      "chains": [
        "bsc"
      ],
      "totalTokens": 2,
      "trackedTokens": 2,
      "wins": 0,
      "losses": 2,
      "winRate": 0,
      "avgReturn": -44.7,
      "score": 0,
      "firstSeen": 1773506911854,
      "topPicks": [
        {
          "symbol": "MOONDOGE",
          "chain": "bsc",
          "change": -4.47212373066357
        },
        {
          "symbol": "元",
          "chain": "bsc",
          "change": -85.01734602636067
        }
      ]
    },
    {
      "address": "0x99fab95434ae3d58c71fa298bed5d53285dd456f",
      "chains": [
        "bsc"
      ],
      "totalTokens": 3,
      "trackedTokens": 2,
      "wins": 0,
      "losses": 2,
      "winRate": 0,
      "avgReturn": -30.9,
      "score": 0,
      "firstSeen": 1773506911854,
      "topPicks": [
        {
          "symbol": "我的刀盾",
          "chain": "bsc",
          "change": -2.0978893799212193
        },
        {
          "symbol": "OPC",
          "chain": "bsc",
          "change": -59.66241790414356
        }
      ]
    },
    {
      "address": "0x0f6fbb464f9c06da4500d3d625b2276236879c7e",
      "chains": [
        "bsc"
      ],
      "totalTokens": 2,
      "trackedTokens": 2,
      "wins": 0,
      "losses": 2,
      "winRate": 0,
      "avgReturn": -30.9,
      "score": 0,
      "firstSeen": 1773506911854,
      "topPicks": [
        {
          "symbol": "Fish",
          "chain": "bsc",
          "change": -11.036969308941165
        },
        {
          "symbol": "Memehouse",
          "chain": "bsc",
          "change": -50.80982894219438
        }
      ]
    },
    {
      "address": "0xc20791b21acca72d837608c33f3fb037993ca356",
      "chains": [
        "bsc"
      ],
      "totalTokens": 2,
      "trackedTokens": 2,
      "wins": 0,
      "losses": 2,
      "winRate": 0,
      "avgReturn": -86.5,
      "score": 0,
      "firstSeen": 1773506911854,
      "topPicks": [
        {
          "symbol": "MoonCat",
          "chain": "bsc",
          "change": -79.21905671128339
        },
        {
          "symbol": "FAFO",
          "chain": "bsc",
          "change": -93.7211149521641
        }
      ]
    },
    {
      "address": "0xb3597de13502f0e9eb8033abee97a518067d23e5",
      "chains": [
        "bsc"
      ],
      "totalTokens": 3,
      "trackedTokens": 3,
      "wins": 0,
      "losses": 3,
      "winRate": 0,
      "avgReturn": -59.1,
      "score": 0,
      "firstSeen": 1773506911854,
      "topPicks": [
        {
          "symbol": "MOONDOGE",
          "chain": "bsc",
          "change": -4.47212373066357
        },
        {
          "symbol": "MoonCat",
          "chain": "bsc",
          "change": -79.21905671128339
        },
        {
          "symbol": "FAFO",
          "chain": "bsc",
          "change": -93.7211149521641
        }
      ]
    },
    {
      "address": "0xc51cc340bf30d186947cec54dfb2f32f9de705dc",
      "chains": [
        "bsc"
      ],
      "totalTokens": 3,
      "trackedTokens": 2,
      "wins": 0,
      "losses": 2,
      "winRate": 0,
      "avgReturn": -95.9,
      "score": 0,
      "firstSeen": 1773506911854,
      "topPicks": [
        {
          "symbol": "FAFO",
          "chain": "bsc",
          "change": -93.7211149521641
        },
        {
          "symbol": "Elon musk",
          "chain": "bsc",
          "change": -98.05949730979835
        }
      ]
    },
    {
      "address": "0xeda3fdb1b9893064ce6d2ea4281432aa527cce57",
      "chains": [
        "bsc"
      ],
      "totalTokens": 3,
      "trackedTokens": 2,
      "wins": 0,
      "losses": 2,
      "winRate": 0,
      "avgReturn": -97.6,
      "score": 0,
      "firstSeen": 1773506911854,
      "topPicks": [
        {
          "symbol": "波龙",
          "chain": "bsc",
          "change": -97.04869173005515
        },
        {
          "symbol": "Elon musk",
          "chain": "bsc",
          "change": -98.05949730979835
        }
      ]
    },
    {
      "address": "0x69cd2138e1de4f1db5dff86e0b12e1d5c0f4e316",
      "chains": [
        "bsc"
      ],
      "totalTokens": 2,
      "trackedTokens": 2,
      "wins": 0,
      "losses": 2,
      "winRate": 0,
      "avgReturn": -49.1,
      "score": 0,
      "firstSeen": 1773506911854,
      "topPicks": [
        {
          "symbol": "MOONDOGE",
          "chain": "bsc",
          "change": -4.47212373066357
        },
        {
          "symbol": "FAFO",
          "chain": "bsc",
          "change": -93.7211149521641
        }
      ]
    },
    {
      "address": "0x7453c2f26632c54a0bae8b67d572eb093785e513",
      "chains": [
        "bsc"
      ],
      "totalTokens": 3,
      "trackedTokens": 2,
      "wins": 0,
      "losses": 2,
      "winRate": 0,
      "avgReturn": -93.3,
      "score": 0,
      "firstSeen": 1773506911854,
      "topPicks": [
        {
          "symbol": "Meme Strategy",
          "chain": "bsc",
          "change": -92.9605455737161
        },
        {
          "symbol": "FAFO",
          "chain": "bsc",
          "change": -93.7211149521641
        }
      ]
    },
    {
      "address": "0xe369226f48159e9192443bd41fe79d60696d8caf",
      "chains": [
        "bsc"
      ],
      "totalTokens": 3,
      "trackedTokens": 3,
      "wins": 0,
      "losses": 3,
      "winRate": 0,
      "avgReturn": -61.5,
      "score": 0,
      "firstSeen": 1773506911854,
      "topPicks": [
        {
          "symbol": "MOONDOGE",
          "chain": "bsc",
          "change": -4.47212373066357
        },
        {
          "symbol": "CLANK",
          "chain": "bsc",
          "change": -86.42805970485583
        },
        {
          "symbol": "FAFO",
          "chain": "bsc",
          "change": -93.7211149521641
        }
      ]
    },
    {
      "address": "0xe4c924b5a3d769214bf4c04818eba040c70bc311",
      "chains": [
        "bsc"
      ],
      "totalTokens": 2,
      "trackedTokens": 2,
      "wins": 0,
      "losses": 2,
      "winRate": 0,
      "avgReturn": -52.5,
      "score": 0,
      "firstSeen": 1773506911854,
      "topPicks": [
        {
          "symbol": "导师",
          "chain": "bsc",
          "change": -11.3708151569477
        },
        {
          "symbol": "FAFO",
          "chain": "bsc",
          "change": -93.7211149521641
        }
      ]
    },
    {
      "address": "0xc90636927e5aafd821d72b8e39da033bf55ed617",
      "chains": [
        "bsc"
      ],
      "totalTokens": 3,
      "trackedTokens": 3,
      "wins": 0,
      "losses": 3,
      "winRate": 0,
      "avgReturn": -63.5,
      "score": 0,
      "firstSeen": 1773506911854,
      "topPicks": [
        {
          "symbol": "MOONDOGE",
          "chain": "bsc",
          "change": -4.47212373066357
        },
        {
          "symbol": "无主之币",
          "chain": "bsc",
          "change": -92.24554571396854
        },
        {
          "symbol": "FAFO",
          "chain": "bsc",
          "change": -93.7211149521641
        }
      ]
    },
    {
      "address": "0xfc392123055ddb8cb192a69e6f6b483deef19f20",
      "chains": [
        "bsc"
      ],
      "totalTokens": 2,
      "trackedTokens": 2,
      "wins": 0,
      "losses": 2,
      "winRate": 0,
      "avgReturn": -48.7,
      "score": 0,
      "firstSeen": 1773506911854,
      "topPicks": [
        {
          "symbol": "MOONDOGE",
          "chain": "bsc",
          "change": -4.47212373066357
        },
        {
          "symbol": "Meme Strategy",
          "chain": "bsc",
          "change": -92.9605455737161
        }
      ]
    },
    {
      "address": "0x6a0ac2e51c2e956b8803fa54c4981ead88df1a71",
      "chains": [
        "bsc"
      ],
      "totalTokens": 2,
      "trackedTokens": 2,
      "wins": 0,
      "losses": 2,
      "winRate": 0,
      "avgReturn": -3.3,
      "score": 0,
      "firstSeen": 1773506911854,
      "topPicks": [
        {
          "symbol": "我的刀盾",
          "chain": "bsc",
          "change": -2.0978893799212193
        },
        {
          "symbol": "MOONDOGE",
          "chain": "bsc",
          "change": -4.47212373066357
        }
      ]
    },
    {
      "address": "0x7aaa92a879cbfcdd188b652619dba95c3bca1f8d",
      "chains": [
        "bsc"
      ],
      "totalTokens": 5,
      "trackedTokens": 4,
      "wins": 0,
      "losses": 4,
      "winRate": 0,
      "avgReturn": -84.7,
      "score": 0,
      "firstSeen": 1773506911854,
      "topPicks": [
        {
          "symbol": "Memrush",
          "chain": "bsc",
          "change": -77.04969422632857
        },
        {
          "symbol": "波龙",
          "chain": "bsc",
          "change": -77.83415715079039
        },
        {
          "symbol": "CLANK",
          "chain": "bsc",
          "change": -86.42805970485583
        },
        {
          "symbol": "波龙",
          "chain": "bsc",
          "change": -97.37666089303639
        }
      ]
    },
    {
      "address": "0x61e13b2adf64d838c93d18830b9777f4b5a6339c",
      "chains": [
        "bsc"
      ],
      "totalTokens": 2,
      "trackedTokens": 2,
      "wins": 0,
      "losses": 2,
      "winRate": 0,
      "avgReturn": -47.4,
      "score": 0,
      "firstSeen": 1773506911854,
      "topPicks": [
        {
          "symbol": "Fight",
          "chain": "bsc",
          "change": -2.519284602892678
        },
        {
          "symbol": "无主之币",
          "chain": "bsc",
          "change": -92.24554571396854
        }
      ]
    },
    {
      "address": "0x183a3300f8939e39cafa6d5801a8a3fd73e4babb",
      "chains": [
        "bsc"
      ],
      "totalTokens": 2,
      "trackedTokens": 2,
      "wins": 0,
      "losses": 2,
      "winRate": 0,
      "avgReturn": -45.9,
      "score": 0,
      "firstSeen": 1773506911854,
      "topPicks": [
        {
          "symbol": "狐狸",
          "chain": "bsc",
          "change": -7.250815648948395
        },
        {
          "symbol": "MOONDOGECOIN",
          "chain": "bsc",
          "change": -84.60505860322087
        }
      ]
    },
    {
      "address": "0x0a05defe3f53ddd4ad66a48204e7f4c63ab96aa4",
      "chains": [
        "bsc"
      ],
      "totalTokens": 2,
      "trackedTokens": 2,
      "wins": 0,
      "losses": 2,
      "winRate": 0,
      "avgReturn": -81.7,
      "score": 0,
      "firstSeen": 1773506911854,
      "topPicks": [
        {
          "symbol": "Memrush",
          "chain": "bsc",
          "change": -77.04969422632857
        },
        {
          "symbol": "CLANK",
          "chain": "bsc",
          "change": -86.42805970485583
        }
      ]
    },
    {
      "address": "0x3888844b70e1bf39d4a4fa360712ff5725a73738",
      "chains": [
        "bsc"
      ],
      "totalTokens": 3,
      "trackedTokens": 3,
      "wins": 0,
      "losses": 3,
      "winRate": 0,
      "avgReturn": -58.2,
      "score": 0,
      "firstSeen": 1773506911854,
      "topPicks": [
        {
          "symbol": "Fish",
          "chain": "bsc",
          "change": -11.036969308941165
        },
        {
          "symbol": "Memrush",
          "chain": "bsc",
          "change": -77.04969422632857
        },
        {
          "symbol": "CLANK",
          "chain": "bsc",
          "change": -86.42805970485583
        }
      ]
    },
    {
      "address": "0x78949af16d097d27a66d1a693b3546acefe062cd",
      "chains": [
        "bsc"
      ],
      "totalTokens": 2,
      "trackedTokens": 2,
      "wins": 1,
      "losses": 1,
      "winRate": 50,
      "avgReturn": -43,
      "score": 0,
      "firstSeen": 1773506911855,
      "topPicks": [
        {
          "symbol": "WUKONG",
          "chain": "bsc",
          "change": 11.30493991265331
        },
        {
          "symbol": "波龙",
          "chain": "bsc",
          "change": -97.37666089303639
        }
      ]
    },
    {
      "address": "0xd06c3e5ade3d8f9c7539a1d1c247b29ba1f7a2af",
      "chains": [
        "base"
      ],
      "totalTokens": 4,
      "trackedTokens": 2,
      "wins": 0,
      "losses": 2,
      "winRate": 0,
      "avgReturn": -40.6,
      "score": 0,
      "firstSeen": 1773508066758,
      "topPicks": [
        {
          "symbol": "MOLT",
          "chain": "base",
          "change": -0.1456610823546663
        },
        {
          "symbol": "BEAN",
          "chain": "base",
          "change": -80.98864494453194
        }
      ]
    },
    {
      "address": "0x7f9148c38aebf08d5f3b0b5db1be101ba1486dca",
      "chains": [
        "base"
      ],
      "totalTokens": 3,
      "trackedTokens": 3,
      "wins": 1,
      "losses": 2,
      "winRate": 33.3,
      "avgReturn": -29.3,
      "score": 0,
      "firstSeen": 1773508066758,
      "topPicks": [
        {
          "symbol": "DUELSMD",
          "chain": "base",
          "change": 5.827908780377871
        },
        {
          "symbol": "MAIAT",
          "chain": "base",
          "change": -37.136564476129166
        },
        {
          "symbol": "GOCHU",
          "chain": "base",
          "change": -56.44428636923674
        }
      ]
    },
    {
      "address": "0xf8f67383ec0d902c72201413b659480616616d52",
      "chains": [
        "base"
      ],
      "totalTokens": 7,
      "trackedTokens": 5,
      "wins": 1,
      "losses": 4,
      "winRate": 20,
      "avgReturn": -28.6,
      "score": 0,
      "firstSeen": 1773508066758,
      "topPicks": [
        {
          "symbol": "LUKSO",
          "chain": "base",
          "change": 7.176785763909217
        },
        {
          "symbol": "cyb3rwr3n",
          "chain": "base",
          "change": -13.512263286004162
        },
        {
          "symbol": "DONUT",
          "chain": "base",
          "change": -14.865207448385451
        },
        {
          "symbol": "MAIAT",
          "chain": "base",
          "change": -37.136564476129166
        },
        {
          "symbol": "Auto",
          "chain": "base",
          "change": -84.42775635272893
        }
      ]
    },
    {
      "address": "0x66231a8b2c0b13a794a3c27bdf25ebb6012fe91b",
      "chains": [
        "base"
      ],
      "totalTokens": 2,
      "trackedTokens": 2,
      "wins": 1,
      "losses": 1,
      "winRate": 50,
      "avgReturn": -28.3,
      "score": 0,
      "firstSeen": 1773508066758,
      "topPicks": [
        {
          "symbol": "LUKSO",
          "chain": "base",
          "change": 7.176785763909217
        },
        {
          "symbol": "HOLO",
          "chain": "base",
          "change": -63.68697514290213
        }
      ]
    },
    {
      "address": "0xdf3ea901ca5be60e02fdea007525a656ab211bd2",
      "chains": [
        "base"
      ],
      "totalTokens": 12,
      "trackedTokens": 7,
      "wins": 3,
      "losses": 4,
      "winRate": 42.9,
      "avgReturn": -13.4,
      "score": 0,
      "firstSeen": 1773508066758,
      "topPicks": [
        {
          "symbol": "SMOL",
          "chain": "base",
          "change": 17.63100836747984
        },
        {
          "symbol": "OIL",
          "chain": "base",
          "change": 1.175473469216646
        },
        {
          "symbol": "NOX",
          "chain": "base",
          "change": 0.14369912130168133
        },
        {
          "symbol": "MOLT",
          "chain": "base",
          "change": -0.1456610823546663
        },
        {
          "symbol": "Dave",
          "chain": "base",
          "change": -10.550890734537044
        }
      ]
    },
    {
      "address": "0xae88643e62a4fda856d1eeee281a90e5fdd57cc6",
      "chains": [
        "base"
      ],
      "totalTokens": 8,
      "trackedTokens": 6,
      "wins": 1,
      "losses": 5,
      "winRate": 16.7,
      "avgReturn": -15,
      "score": 0,
      "firstSeen": 1773508066758,
      "topPicks": [
        {
          "symbol": "SMOL",
          "chain": "base",
          "change": 17.63100836747984
        },
        {
          "symbol": "MOLT",
          "chain": "base",
          "change": -0.1456610823546663
        },
        {
          "symbol": "TOWNS",
          "chain": "base",
          "change": -0.996472381853253
        },
        {
          "symbol": "Dave",
          "chain": "base",
          "change": -10.550890734537044
        },
        {
          "symbol": "VANCE",
          "chain": "base",
          "change": -21.4602757577122
        }
      ]
    },
    {
      "address": "0xc30cf256dfc731193a4fe2b02c89bf1815ec70a5",
      "chains": [
        "base"
      ],
      "totalTokens": 2,
      "trackedTokens": 2,
      "wins": 0,
      "losses": 2,
      "winRate": 0,
      "avgReturn": -43.1,
      "score": 0,
      "firstSeen": 1773508066758,
      "topPicks": [
        {
          "symbol": "Conway",
          "chain": "base",
          "change": -27.76963523419424
        },
        {
          "symbol": "OpenVenice",
          "chain": "base",
          "change": -58.400782688563005
        }
      ]
    },
    {
      "address": "0x9d14b5f3fc5406d23211d653186a393b1bf75682",
      "chains": [
        "base"
      ],
      "totalTokens": 2,
      "trackedTokens": 2,
      "wins": 1,
      "losses": 1,
      "winRate": 50,
      "avgReturn": -8.5,
      "score": 0,
      "firstSeen": 1773508066758,
      "topPicks": [
        {
          "symbol": "STAKR",
          "chain": "base",
          "change": 63.97824260792292
        },
        {
          "symbol": "BEAN",
          "chain": "base",
          "change": -80.98864494453194
        }
      ]
    },
    {
      "address": "0x6f7ac662f07f58a5c317a2852e0cc2d6bf886213",
      "chains": [
        "base"
      ],
      "totalTokens": 3,
      "trackedTokens": 3,
      "wins": 2,
      "losses": 1,
      "winRate": 66.7,
      "avgReturn": -11.4,
      "score": 0,
      "firstSeen": 1773508066758,
      "topPicks": [
        {
          "symbol": "JUNO",
          "chain": "base",
          "change": 40.234492206838354
        },
        {
          "symbol": "NOX",
          "chain": "base",
          "change": 0.14369912130168133
        },
        {
          "symbol": "POLAR",
          "chain": "base",
          "change": -74.51310891210787
        }
      ]
    },
    {
      "address": "0x981837fcc116557663d3a3692700f9b89739323f",
      "chains": [
        "base"
      ],
      "totalTokens": 3,
      "trackedTokens": 3,
      "wins": 1,
      "losses": 2,
      "winRate": 33.3,
      "avgReturn": -31.7,
      "score": 0,
      "firstSeen": 1773508066758,
      "topPicks": [
        {
          "symbol": "GITLAWB",
          "chain": "base",
          "change": 7.4715243270023475
        },
        {
          "symbol": "VANCE",
          "chain": "base",
          "change": -21.4602757577122
        },
        {
          "symbol": "BEAN",
          "chain": "base",
          "change": -80.98864494453194
        }
      ]
    },
    {
      "address": "0x12e16f99f055e96494963c8dd27690d1e0ad631f",
      "chains": [
        "base"
      ],
      "totalTokens": 2,
      "trackedTokens": 2,
      "wins": 1,
      "losses": 1,
      "winRate": 50,
      "avgReturn": -23.6,
      "score": 0,
      "firstSeen": 1773508066759,
      "topPicks": [
        {
          "symbol": "Doppel",
          "chain": "base",
          "change": 13.49120781765134
        },
        {
          "symbol": "YARR",
          "chain": "base",
          "change": -60.69581325699003
        }
      ]
    },
    {
      "address": "0xd98204aa48a6ea0d541b506303d00d252dbc17f2",
      "chains": [
        "base"
      ],
      "totalTokens": 3,
      "trackedTokens": 3,
      "wins": 0,
      "losses": 3,
      "winRate": 0,
      "avgReturn": -47,
      "score": 0,
      "firstSeen": 1773508066759,
      "topPicks": [
        {
          "symbol": "MOLT",
          "chain": "base",
          "change": -0.1456610823546663
        },
        {
          "symbol": "GOCHU",
          "chain": "base",
          "change": -56.44428636923674
        },
        {
          "symbol": "Auto",
          "chain": "base",
          "change": -84.42775635272893
        }
      ]
    },
    {
      "address": "0x7c40aacb32fe250b6d7f1caea0af2f63ac526a7c",
      "chains": [
        "base"
      ],
      "totalTokens": 2,
      "trackedTokens": 2,
      "wins": 0,
      "losses": 2,
      "winRate": 0,
      "avgReturn": -65.5,
      "score": 0,
      "firstSeen": 1773508066759,
      "topPicks": [
        {
          "symbol": "GOCHU",
          "chain": "base",
          "change": -56.44428636923674
        },
        {
          "symbol": "POLAR",
          "chain": "base",
          "change": -74.51310891210787
        }
      ]
    },
    {
      "address": "0x04cf495074a5a33aba02e3dc2cd38710a369be07",
      "chains": [
        "base"
      ],
      "totalTokens": 3,
      "trackedTokens": 2,
      "wins": 0,
      "losses": 2,
      "winRate": 0,
      "avgReturn": -14,
      "score": 0,
      "firstSeen": 1773508066759,
      "topPicks": [
        {
          "symbol": "MOLT",
          "chain": "base",
          "change": -0.1456610823546663
        },
        {
          "symbol": "Conway",
          "chain": "base",
          "change": -27.76963523419424
        }
      ]
    },
    {
      "address": "0xd9b5533af7a7bcb948a28dc86ac16384f5b798fa",
      "chains": [
        "base"
      ],
      "totalTokens": 2,
      "trackedTokens": 2,
      "wins": 1,
      "losses": 1,
      "winRate": 50,
      "avgReturn": -11.7,
      "score": 0,
      "firstSeen": 1773508066759,
      "topPicks": [
        {
          "symbol": "JUNO",
          "chain": "base",
          "change": 40.234492206838354
        },
        {
          "symbol": "HOLO",
          "chain": "base",
          "change": -63.68697514290213
        }
      ]
    }
  ]
}